f.py
p2f-0.0.1.dist-info/DESCRIPTION.rst
p2f-0.0.1.dist-info/METADATA
p2f-0.0.1.dist-info/RECORD
p2f-0.0.1.dist-info/WHEEL
p2f-0.0.1.dist-info/metadata.json
p2f-0.0.1.dist-info/pbr.json
p2f-0.0.1.dist-info/top_level.txt
